desisky/__about__.py
desisky/__init__.py
desisky/data/__init__.py
desisky/data/_core.py
desisky/data/_enrich.py
desisky/data/skyspec.py
desisky/inference/__init__.py
desisky/inference/sampling.py
desisky/io/__init__.py
desisky/io/model_io.py
desisky/models/__init__.py
desisky/models/broadband.py
desisky/models/ldm.py
desisky/models/vae.py
desisky/scripts/__init__.py
desisky/scripts/download_data.py
desisky/scripts/train_vae.py
desisky/training/README.md
desisky/training/__init__.py
desisky/training/dataset.py
desisky/training/ldm_trainer.py
desisky/training/losses.py
desisky/training/trainer.py
desisky/training/vae_losses.py
desisky/training/vae_trainer.py
desisky/visualization/__init__.py
desisky/visualization/plots.py
desisky/weights/broadband_weights.eqx
desisky-0.3.0.dist-info/METADATA
desisky-0.3.0.dist-info/WHEEL
desisky-0.3.0.dist-info/entry_points.txt
desisky-0.3.0.dist-info/licenses/LICENSE.txt
desisky-0.3.0.dist-info/RECORD
