Metadata-Version: 2.4
Name: desisky
Version: 0.3.0
Project-URL: Documentation, https://github.com/MatthewDowicz/desisky#readme
Project-URL: Issues, https://github.com/MatthewDowicz/desisky/issues
Project-URL: Source, https://github.com/MatthewDowicz/desisky
Author-email: MatthewDowicz <mdowicz@uci.edu>
License-Expression: MIT
License-File: LICENSE.txt
Keywords: DESI,astronomy,generative model,sky spectra
Classifier: Development Status :: 4 - Beta
Classifier: Programming Language :: Python
Classifier: Programming Language :: Python :: 3.9
Classifier: Programming Language :: Python :: 3.10
Classifier: Programming Language :: Python :: 3.11
Classifier: Programming Language :: Python :: 3.12
Classifier: Programming Language :: Python :: Implementation :: CPython
Classifier: Programming Language :: Python :: Implementation :: PyPy
Requires-Python: >=3.10
Requires-Dist: numpy
Requires-Dist: requests
Requires-Dist: scipy
Provides-Extra: all
Requires-Dist: astropy; extra == 'all'
Requires-Dist: equinox; extra == 'all'
Requires-Dist: fitsio; extra == 'all'
Requires-Dist: jax; extra == 'all'
Requires-Dist: matplotlib; extra == 'all'
Requires-Dist: optax; extra == 'all'
Requires-Dist: pandas; extra == 'all'
Requires-Dist: speclite; extra == 'all'
Requires-Dist: torch; extra == 'all'
Provides-Extra: cpu
Requires-Dist: equinox; extra == 'cpu'
Requires-Dist: jax; extra == 'cpu'
Requires-Dist: optax; extra == 'cpu'
Requires-Dist: torch; extra == 'cpu'
Provides-Extra: cuda12
Requires-Dist: equinox; extra == 'cuda12'
Requires-Dist: jax[cuda12]; extra == 'cuda12'
Requires-Dist: optax; extra == 'cuda12'
Requires-Dist: torch; extra == 'cuda12'
Provides-Extra: data
Requires-Dist: astropy; extra == 'data'
Requires-Dist: fitsio; extra == 'data'
Requires-Dist: pandas; extra == 'data'
Requires-Dist: speclite; extra == 'data'
Provides-Extra: train
Requires-Dist: equinox; extra == 'train'
Requires-Dist: jax; extra == 'train'
Requires-Dist: optax; extra == 'train'
Requires-Dist: torch; extra == 'train'
Provides-Extra: viz
Requires-Dist: matplotlib; extra == 'viz'
